[
  {"id": "G4-T1", "gate": "gate-4-lifepilot", "agent": "master-planner-agent", "status": "in-progress", "title": "读取 mimo-lifepilot scaffold 并制定独立化计划"},
  {"id": "G4-T2", "gate": "gate-4-lifepilot", "agent": "frontend-agent", "status": "pending", "title": "实现独立 apps/web LifePilot 前端"},
  {"id": "G4-T3", "gate": "gate-4-lifepilot", "agent": "backend-agent", "status": "pending", "title": "实现独立 apps/api LifePilot 后端"},
  {"id": "G4-T4", "gate": "gate-4-lifepilot", "agent": "frontend-agent", "status": "pending", "title": "接入 SplineScene 或 fallback 视觉系统"},
  {"id": "G4-T5", "gate": "gate-4-lifepilot", "agent": "qa-agent", "status": "pending", "title": "添加并运行 API/前端测试"},
  {"id": "G4-T6", "gate": "gate-4-lifepilot", "agent": "release-agent", "status": "pending", "title": "commit/push mimo-lifepilot 并更新 Portfolio Hub"},
  {"id": "G4-T7", "gate": "gate-4-lifepilot", "agent": "harness-controller-agent", "status": "pending", "title": "更新 Gate 4 evidence 和 STATUS"}
]